{
  "pxraX4SEmSw": {
    "title": "Lost",
    "url": "https://www.youtube.com/watch?v=pxraX4SEmSw",
    "id": "pxraX4SEmSw",
    "duration": "PT4M49S",
    "thumbnail": "https://i.ytimg.com/vi/pxraX4SEmSw/default.jpg"
  },
  "532tVKlh1Uc": {
    "title": "Fortnite - Scenario Emote (Beat)",
    "url": "https://www.youtube.com/watch?v=532tVKlh1Uc",
    "id": "532tVKlh1Uc",
    "duration": "PT2M1S",
    "thumbnail": "https://i.ytimg.com/vi/532tVKlh1Uc/default.jpg"
  },
  "vecSVX1QYbQ": {
    "title": "iKON - ‘사랑을 했다(LOVE SCENARIO)’ M/V",
    "url": "https://youtube.com/watch?v=vecSVX1QYbQ",
    "id": "vecSVX1QYbQ",
    "duration": "PT3M32S",
    "thumbnail": "https://i.ytimg.com/vi/vecSVX1QYbQ/hq720.jpg"
  }
}
